taleb_analysis/__init__.py
taleb_analysis/main.py
taleb_analysis/prompts.py
taleb_analysis-2025.12.21155436.dist-info/METADATA
taleb_analysis-2025.12.21155436.dist-info/WHEEL
taleb_analysis-2025.12.21155436.dist-info/top_level.txt
taleb_analysis-2025.12.21155436.dist-info/RECORD
