Metadata-Version: 2.4
Name: taleb-analysis
Version: 2025.12.21155436
Summary: A new package would provide a text input describing a system, event, or scenario, and return a structured analysis based on Nassim Taleb's concepts of Black Swan events and antifragility. It would ide
Author-email: taleb-analysis <hi@eugene.plus>
License: MIT
Project-URL: Homepage, https://github.com/chigwell/taleb-analysis
Requires-Python: >=3.9
Requires-Dist: langchain-llm7>=0.0.0
Requires-Dist: llmatch-messages>=0.0.0
Requires-Dist: langchain-core>=0.3.0
